xev_data-0.1.7.dist-info/METADATA
xev_data-0.1.7.dist-info/WHEEL
xev_data-0.1.7.dist-info/licenses/LICENSE
xdata/__init__.py
xdata/__version__.py
xdata/database.py
xdata/registry.py
xdata/connection.py
xdata/error.py
xdata/attributes.py
xdata/address.py
xdata/dataset.py
xdata/group.py
xdata/files/__init__.py
xdata/files/hash.dat
xev_data-0.1.7.dist-info/RECORD
