Metadata-Version: 2.4
Name: xev-data
Version: 0.1.7
Summary: Vera's database tools for python
Keywords: hdf5,database management
Author-Email: Vera Delfavero <xevra86@gmail.com>
Maintainer-Email: Vera Delfavero <xevra86@gmail.com>
License-File: LICENSE
Classifier: Development Status :: 3 - Alpha
Classifier: Programming Language :: Python :: 3
Classifier: Operating System :: OS Independent
Classifier: Intended Audience :: Science/Research
Classifier: Topic :: Scientific/Engineering :: Astronomy
Classifier: Topic :: Scientific/Engineering :: Physics
Classifier: Topic :: Scientific/Engineering :: Information Analysis
Project-URL: Homepage, https://gitlab.com/xevra/xev-data
Project-URL: Bug Reports,  https://gitlab.com/xevra/xev-data/issues
Requires-Python: >=3.6
Requires-Dist: numpy>=1.16
Requires-Dist: h5py>=2.10.0
Requires-Dist: tqdm
Requires-Dist: requests
